greport/__init__.py
greport/greport.py
greport/template.html
greport-0.1.10.dist-info/LICENSE
greport-0.1.10.dist-info/METADATA
greport-0.1.10.dist-info/WHEEL
greport-0.1.10.dist-info/entry_points.txt
greport-0.1.10.dist-info/top_level.txt
greport-0.1.10.dist-info/RECORD
