Metadata-Version: 2.1
Name: greport
Version: 0.1.10
Summary: Generate html from googletest xml file
Home-page: https://github.com/niedong/greport
Author: niedong
Author-email: niedong0816@126.com
License: UNKNOWN
Platform: UNKNOWN
License-File: LICENSE
Requires-Dist: jinja2
